epitope_aligner/__init__.py
epitope_aligner/examples.py
epitope_aligner/map.py
epitope_aligner/stretch.py
epitope_aligner/utils.py
epitope_aligner-0.1.3.dist-info/METADATA
epitope_aligner-0.1.3.dist-info/WHEEL
epitope_aligner-0.1.3.dist-info/licenses/LICENSE
epitope_aligner-0.1.3.dist-info/RECORD
