Metadata-Version: 2.3
Name: epitope_aligner
Version: 0.1.3
Summary: Easily map epitope coordinates between sequences in an alignment
Project-URL: homepage, https://github.com/BarinthusBio/epitope_aligner
Project-URL: documentation, https://barinthusbio.github.io/epitope_aligner/epitope_aligner.html
Project-URL: issues, https://github.com/BarinthusBio/epitope_aligner/issues
Author-email: David Wells <david.wells@barinthusbio.com>
License: MIT License
Requires-Python: >=3.10
Requires-Dist: biopython
Requires-Dist: matplotlib
Requires-Dist: pandas
Requires-Dist: scipy
